{
  "guid": "https://news.ycombinator.com/item?id=46701733",
  "title": "<h1><a href=\"https://etn.se/index.php/nyheter/72808-curl-removes-bug-bounties.html\" target=\"_blank\">cURL removes bug bounties</a></h1>",
  "link": "https://etn.se/index.php/nyheter/72808-curl-removes-bug-bounties.html",
  "pubDate": "Wed, 21 Jan 2026 06:07:03 +0000",
  "description": "\n<p>Article URL: <a href=\"https://etn.se/index.php/nyheter/72808-curl-removes-bug-bounties.html\">https://etn.se/index.php/nyheter/72808-curl-removes-bug-bounties.html</a></p>\n<p>Comments URL: <a href=\"https://news.ycombinator.com/item?id=46701733\">https://news.ycombinator.com/item?id=46701733</a></p>\n<p>Points: 255</p>\n<p># Comments: 142</p>\n",
  "timestamp": 1768975623000,
  "source": "daa59745c6e0",
  "category": ""
}