{
  "guid": "https://old.reddit.com/r/userexperience/comments/1j1vkqr/how_many_ux_designers_are_straight_up_lying_about/",
  "title": "<h1><a href=\"https://old.reddit.com/r/userexperience/comments/1j1vkqr/how_many_ux_designers_are_straight_up_lying_about/\" target=\"_blank\">How many ux designers are straight up lying about their job history?</a></h1>",
  "link": "https://old.reddit.com/r/userexperience/comments/1j1vkqr/how_many_ux_designers_are_straight_up_lying_about/",
  "pubDate": "2025-03-02T17:03:23.000Z",
  "description": "<div><p>Based on this post. It seems like Junior designers have nothing to lose from lying about their job history. </p> <p><a href=\"https://www.reddit.com/r/UXDesign/s/kg9Hu6rvd5\">https://www.reddit.com/r/UXDesign/s/kg9Hu6rvd5</a></p> <p>Even if they get discovered that they lied, they weren't going to get the job by being honest anyways. I'm sure a lot slip through the cracks and end up getting the job.</p> <p>In your experience, is this very common? </p> </div>   submitted by   <a href=\"https://old.reddit.com/user/Gandalf-and-Frodo\"> /u/Gandalf-and-Frodo </a> <br /> <span><a href=\"https://old.reddit.com/r/userexperience/comments/1j1vkqr/how_many_ux_designers_are_straight_up_lying_about/\">[link]</a></span>   <span><a href=\"https://old.reddit.com/r/userexperience/comments/1j1vkqr/how_many_ux_designers_are_straight_up_lying_about/\">[comments]</a></span>",
  "timestamp": 1740935003000,
  "source": "7f7c52b69f7e",
  "category": ""
}