{
  "guid": "https://www.bbc.co.uk/news/10628994#5",
  "title": "<h1><a href=\"https://www.bbc.co.uk/news/10628994?at_medium=RSS&at_campaign=rss\" target=\"_blank\">BBC News app</a></h1>",
  "link": "https://www.bbc.co.uk/news/10628994?at_medium=RSS&at_campaign=rss",
  "pubDate": "Wed, 30 Apr 2025 14:04:28 GMT",
  "description": "Top stories, breaking news, live reporting, and follow news topics that match your interests",
  "timestamp": 1746021868000,
  "source": "1539c6424f4f",
  "category": ""
}